burrowts/__init__.py
burrowts/burrowts.py
tests/__init__.py
tests/test_burrowts.py
burrowts-0.0.1.dist-info/LICENSE
burrowts-0.0.1.dist-info/METADATA
burrowts-0.0.1.dist-info/WHEEL
burrowts-0.0.1.dist-info/top_level.txt
burrowts-0.0.1.dist-info/RECORD
