Metadata-Version: 2.1
Name: burrowts
Version: 0.0.1
Summary: Simple plug and play timeseries database for storing and retreiving time-stamped values
Home-page: https://github.com/iunary/burrowts
Author: Yusuf
Author-email: contact@yusuf.im
License: MIT
Keywords: timeseries,stime-stamped,timeseries store,time series,thread-safe
Platform: UNKNOWN
Classifier: Programming Language :: Python :: 3
Classifier: Operating System :: OS Independent
Requires-Python: >=3.8
License-File: LICENSE
